{
  "properties": {
    "connectionReferences": {
      "shared_microsoftforms": {
        "runtimeSource": "embedded",
        "connection": {
          "connectionReferenceLogicalName": "crd52_sharedmicrosoftforms_8688c"
        },
        "api": {
          "name": "shared_microsoftforms"
        }
      },
      "shared_sendmail_1": {
        "runtimeSource": "embedded",
        "connection": {
          "connectionReferenceLogicalName": "crd52_sharedsendmail_1d8ed"
        },
        "api": {
          "name": "shared_sendmail"
        }
      }
    },
    "definition": {
      "$schema": "https://schema.management.azure.com/providers/Microsoft.Logic/schemas/2016-06-01/workflowdefinition.json#",
      "contentVersion": "1.0.0.0",
      "parameters": {
        "$connections": {
          "defaultValue": {},
          "type": "Object"
        },
        "$authentication": {
          "defaultValue": {},
          "type": "SecureObject"
        }
      },
      "triggers": {
        "Exit_Interview_completed": {
          "splitOn": "@triggerOutputs()?['body/value']",
          "metadata": {
            "operationMetadataId": "d37148db-5357-4f68-8134-0243f86d2117"
          },
          "type": "OpenApiConnectionWebhook",
          "inputs": {
            "host": {
              "connectionName": "shared_microsoftforms",
              "operationId": "CreateFormWebhook",
              "apiId": "/providers/Microsoft.PowerApps/apis/shared_microsoftforms"
            },
            "parameters": {
              "form_id": "U5nD0tuoPEyX8tLcdvs-LPBNuh_5AHdLmNbEyqV8motUNVIyWUhJNVZKVVMwTzZFRTgyVE5CMEpNVy4u"
            },
            "authentication": "@parameters('$authentication')"
          }
        }
      },
      "actions": {
        "Get_response_details": {
          "runAfter": {},
          "metadata": {
            "operationMetadataId": "4e8138ce-d762-42ad-84f1-bd7ee58060b8"
          },
          "type": "OpenApiConnection",
          "inputs": {
            "host": {
              "connectionName": "shared_microsoftforms",
              "operationId": "GetFormResponseById",
              "apiId": "/providers/Microsoft.PowerApps/apis/shared_microsoftforms"
            },
            "parameters": {
              "form_id": "U5nD0tuoPEyX8tLcdvs-LPBNuh_5AHdLmNbEyqV8motUNVIyWUhJNVZKVVMwTzZFRTgyVE5CMEpNVy4u",
              "response_id": "@triggerOutputs()?['body/resourceData/responseId']"
            },
            "authentication": "@parameters('$authentication')"
          }
        },
        "Send_email_to_HR": {
          "runAfter": {
            "Get_response_details": [
              "Succeeded"
            ]
          },
          "metadata": {
            "operationMetadataId": "8229e9e3-3e07-4a86-b745-f9a865d1f201"
          },
          "type": "OpenApiConnection",
          "inputs": {
            "host": {
              "connectionName": "shared_sendmail_1",
              "operationId": "SendEmailV3",
              "apiId": "/providers/Microsoft.PowerApps/apis/shared_sendmail"
            },
            "parameters": {
              "request/to": "testaskhr@harrow.gov.uk",
              "request/subject": "An exit interview has been completed by @{outputs('Get_response_details')?['body/responder']}",
              "request/text": "<p>Please log into Microsoft forms to retreive the details.</p>"
            },
            "authentication": "@parameters('$authentication')"
          }
        }
      }
    },
    "templateName": null
  },
  "schemaVersion": "1.0.0.0"
}